hhc/__init__.py
hhc/coding.py
hhc/hhc_test.py
hhc/num_encode_base64.py
hhc-3.0.2.dist-info/LICENSE
hhc-3.0.2.dist-info/METADATA
hhc-3.0.2.dist-info/WHEEL
hhc-3.0.2.dist-info/top_level.txt
hhc-3.0.2.dist-info/RECORD
