Metadata-Version: 2.1
Name: hhc
Version: 3.0.2
Summary: The best way to express a number in a URL.
Home-page: https://github.com/aljungberg/hhc
Author: Alexander Ljungberg
Author-email: aljungberg@slevenbits.com
License: UNKNOWN
Keywords: base64,hexahexacontadecimal,hhc,base66,url
Platform: UNKNOWN
Classifier: Programming Language :: Python :: 2
Classifier: Programming Language :: Python :: 2.7
Classifier: Programming Language :: Python :: 3
Classifier: Programming Language :: Python :: 3.4
Classifier: Programming Language :: Python :: 3.5
Classifier: Programming Language :: Python :: 3.6
Classifier: Programming Language :: Python :: 3.7
Classifier: Development Status :: 5 - Production/Stable
Classifier: Intended Audience :: Developers
Classifier: Topic :: Software Development :: Libraries
Classifier: License :: OSI Approved :: BSD License
Classifier: Operating System :: POSIX
Requires-Python: >=2.7, !=3.0.*, !=3.1.*, !=3.2.*, !=3.3.*
